Workbook
Name Slicer_expenses_category: #N/A
Name Slicer_product_category1: #N/A
Name Slicer_year1: #N/A

Sheet STOCK_IN
A1: date | B1: PRODUCTS CATEGORY | C1: PRODUCTS | D1: COST PRICE | E1: SELLING PRICE
B2: CHARGERS | C2: SHPLUS SH-A1036 | D2: 4300 | E2: 7500
B3: CHARGERS | C3: 15 PROMAX HEAD | D3: 3600 | E3: 5500
B4: CHARGERS | C4: SHPLUS SH-PD 14 | D4: 5900 | E4: 9000
B5: CHARGERS | C5: SHPLUS A 4010 | D5: 4100 | E5: 7000
B6: CHARGERS | C6: IPHONE 14 PROMAX CHARGER | D6: 4950 | E6: 8000
B7: CHARGERS | C7: I PHONE XS MAX | D7: 1950 | E7: 3000
B8: CHARGERS | C8: 45W PD ADAPTOR | D8: 6250 | E8: 9000
B9: CHARGERS | C9: SHPLUS A 4023 | D9: 3300 | E9: 4500
B10: CHARGERS | C10: SHPLUS A 1004 | D10: 4000 | E10: 6000
B11: CHARGERS | C11: SHPLUS A 1045 | D11: 2550 | E11: 4500
B12: CHARGERS | C12: SAMSUN S7 | D12: 1650 | E12: 3000
B13: CHARGERS | C13: SAMSUN PD FAST CHARGING | D13: 5000 | E13: 7000
... B117: PHONES | C117: TECNO SPARK 40 | D117: 137000 | E117: 145000

Sheet SALES
A1: date | B1: sales_id | C1: product_category | D1: products | E1: quantity | F1: unit_price | G1: total_amount | H1: months | I1: year
A2: 44940 | B2: SAL05117 | C2: CHARGERS | D2: 15 PROMAX HEAD | E2: 8 | F2: {=_xlfn.XLOOKUP(SALES!$D2,TRIM(Table5[PRODUCTS]),Table5[SELLING PRICE])} -> 5500 | G2: =PRODUCT(E2:F2) -> 44000 | H2: =TEXT(A2, "mmm") -> Jan | I2: =YEAR(SALES!$A2) -> 2023
A3: 44941 | B3: SAL02268 | C3: CHARGERS | D3: 15 PROMAX HEAD | E3: 12 | F3: {=_xlfn.XLOOKUP(SALES!$D3,TRIM(Table5[PRODUCTS]),Table5[SELLING PRICE])} -> 5500 | G3: =PRODUCT(E3:F3) -> 66000 | H3: =TEXT(A3, "mmm") -> Jan | I3: =YEAR(SALES!$A3) -> 2023
A4: 44942 | B4: SAL02085 | C4: CHARGERS | D4: 15 PROMAX HEAD | E4: 7 | F4: {=_xlfn.XLOOKUP(SALES!$D4,TRIM(Table5[PRODUCTS]),Table5[SELLING PRICE])} -> 5500 | G4: =PRODUCT(E4:F4) -> 38500 | H4: =TEXT(A4, "mmm") -> Jan | I4: =YEAR(SALES!$A4) -> 2023
A5: 2023-02-12 | B5: SAL02897 | C5: CHARGERS | D5: 15 PROMAX HEAD | E5: 12 | F5: {=_xlfn.XLOOKUP(SALES!$D5,TRIM(Table5[PRODUCTS]),Table5[SELLING PRICE])} -> 5500 | G5: =PRODUCT(E5:F5) -> 66000 | H5: =TEXT(A5, "mmm") -> Feb | I5: =YEAR(SALES!$A5) -> 2023
A6: 2023-03-01 | B6: SAL02002 | C6: CHARGERS | D6: 15 PROMAX HEAD | E6: 8 | F6: {=_xlfn.XLOOKUP(SALES!$D6,TRIM(Table5[PRODUCTS]),Table5[SELLING PRICE])} -> 5500 | G6: =PRODUCT(E6:F6) -> 44000 | H6: =TEXT(A6, "mmm") -> Mar | I6: =YEAR(SALES!$A6) -> 2023
A7: 2023-03-02 | B7: SAL04900 | C7: CHARGERS | D7: 15 PROMAX HEAD | E7: 14 | F7: {=_xlfn.XLOOKUP(SALES!$D7,TRIM(Table5[PRODUCTS]),Table5[SELLING PRICE])} -> 5500 | G7: =PRODUCT(E7:F7) -> 77000 | H7: =TEXT(A7, "mmm") -> Mar | I7: =YEAR(SALES!$A7) -> 2023
A8: 2023-03-19 | B8: SAL05553 | C8: CHARGERS | D8: 15 PROMAX HEAD | E8: 4 | F8: {=_xlfn.XLOOKUP(SALES!$D8,TRIM(Table5[PRODUCTS]),Table5[SELLING PRICE])} -> 5500 | G8: =PRODUCT(E8:F8) -> 22000 | H8: =TEXT(A8, "mmm") -> Mar | I8: =YEAR(SALES!$A8) -> 2023
A9: 2023-04-11 | B9: SAL04198 | C9: CHARGERS | D9: 15 PROMAX HEAD | E9: 14 | F9: {=_xlfn.XLOOKUP(SALES!$D9,TRIM(Table5[PRODUCTS]),Table5[SELLING PRICE])} -> 5500 | G9: =PRODUCT(E9:F9) -> 77000 | H9: =TEXT(A9, "mmm") -> Apr | I9: =YEAR(SALES!$A9) -> 2023
A10: 2023-04-17 | B10: SAL05464 | C10: CHARGERS | D10: 15 PROMAX HEAD | E10: 8 | F10: {=_xlfn.XLOOKUP(SALES!$D10,TRIM(Table5[PRODUCTS]),Table5[SELLING PRICE])} -> 5500 | G10: =PRODUCT(E10:F10) -> 44000 | H10: =TEXT(A10, "mmm") -> Apr | I10: =YEAR(SALES!$A10) -> 2023
A11: 2023-04-22 | B11: SAL03699 | C11: CHARGERS | D11: 15 PROMAX HEAD | E11: 11 | F11: {=_xlfn.XLOOKUP(SALES!$D11,TRIM(Table5[PRODUCTS]),Table5[SELLING PRICE])} -> 5500 | G11: =PRODUCT(E11:F11) -> 60500 | H11: =TEXT(A11, "mmm") -> Apr | I11: =YEAR(SALES!$A11) -> 2023
A12: 2023-05-02 | B12: SAL00542 | C12: CHARGERS | D12: 15 PROMAX HEAD | E12: 11 | F12: {=_xlfn.XLOOKUP(SALES!$D12,TRIM(Table5[PRODUCTS]),Table5[SELLING PRICE])} -> 5500 | G12: =PRODUCT(E12:F12) -> 60500 | H12: =TEXT(A12, "mmm") -> May | I12: =YEAR(SALES!$A12) -> 2023
A13: 2023-05-12 | B13: SAL02797 | C13: CHARGERS | D13: 15 PROMAX HEAD | E13: 3 | F13: {=_xlfn.XLOOKUP(SALES!$D13,TRIM(Table5[PRODUCTS]),Table5[SELLING PRICE])} -> 5500 | G13: =PRODUCT(E13:F13) -> 16500 | H13: =TEXT(A13, "mmm") -> May | I13: =YEAR(SALES!$A13) -> 2023
A14: 2023-05-30 | B14: SAL03799 | C14: CHARGERS | D14: 15 PROMAX HEAD | E14: 2 | F14: {=_xlfn.XLOOKUP(SALES!$D14,TRIM(Table5[PRODUCTS]),Table5[SELLING PRICE])} -> 5500 | G14: =PRODUCT(E14:F14) -> 11000 | H14: =TEXT(A14, "mmm") -> May | I14: =YEAR(SALES!$A14) -> 2023
A15: 2023-06-23 | B15: SAL01204 | C15: CHARGERS | D15: 15 PROMAX HEAD | E15: 9 | F15: {=_xlfn.XLOOKUP(SALES!$D15,TRIM(Table5[PRODUCTS]),Table5[SELLING PRICE])} -> 5500 | G15: =PRODUCT(E15:F15) -> 49500 | H15: =TEXT(A15, "mmm") -> Jun | I15: =YEAR(SALES!$A15) -> 2023
A16: 2023-06-30 | B16: SAL04070 | C16: CHARGERS | D16: 15 PROMAX HEAD | E16: 10 | F16: {=_xlfn.XLOOKUP(SALES!$D16,TRIM(Table5[PRODUCTS]),Table5[SELLING PRICE])} -> 5500 | G16: =PRODUCT(E16:F16) -> 55000 | H16: =TEXT(A16, "mmm") -> Jun | I16: =YEAR(SALES!$A16) -> 2023
... A6001: 2025-12-27 | B6001: SAL05595 | C6001: MOUSE | D6001: WIRELESS MOUSE 2.4GHz | E6001: 15 | F6001: {=_xlfn.XLOOKUP(SALES!$D6001,TRIM(Table5[PRODUCTS]),Table5[SELLING PRICE])} -> 4000 | G6001: =PRODUCT(E6001:F6001) -> 60000 | H6001: =TEXT(A6001, "mmm") -> Dec | I6001: =YEAR(SALES!$A6001) -> 2025

Sheet EXPENSES
A1: date | B1: expenses_category | C1: description | D1: amount | E1: month | F1: year
A2: 2023-01-01 | B2: Marketing | C2: Flyer Printing | D2: 16218 | E2: =TEXT(A2, "mmm") -> Jan | F2: =YEAR(Table7[[#This Row],[date]]) -> 2023
A3: 2023-01-01 | B3: Transportation | C3: Bike Maintenance | D3: 5933 | E3: =TEXT(A3, "mmm") -> Jan | F3: =YEAR(Table7[[#This Row],[date]]) -> 2023
A4: 2023-01-01 | B4: Transportation | C4: Bike Maintenance | D4: 11247 | E4: =TEXT(A4, "mmm") -> Jan | F4: =YEAR(Table7[[#This Row],[date]]) -> 2023
A5: 2023-01-02 | B5: Rent | C5: Office Rent | D5: 94832 | E5: =TEXT(A5, "mmm") -> Jan | F5: =YEAR(Table7[[#This Row],[date]]) -> 2023
A6: 2023-01-03 | B6: Transportation | C6: Bike Maintenance | D6: 5440 | E6: =TEXT(A6, "mmm") -> Jan | F6: =YEAR(Table7[[#This Row],[date]]) -> 2023
A7: 2023-01-03 | B7: Salaries | C7: Staff Salary | D7: 44645 | E7: =TEXT(A7, "mmm") -> Jan | F7: =YEAR(Table7[[#This Row],[date]]) -> 2023
A8: 2023-01-03 | B8: Miscellaneous | C8: Unexpected Expense | D8: 4447 | E8: =TEXT(A8, "mmm") -> Jan | F8: =YEAR(Table7[[#This Row],[date]]) -> 2023
A9: 2023-01-03 | B9: Transportation | C9: Bike Maintenance | D9: 3256 | E9: =TEXT(A9, "mmm") -> Jan | F9: =YEAR(Table7[[#This Row],[date]]) -> 2023
A10: 2023-01-04 | B10: Rent | C10: Shop Rent | D10: 122715 | E10: =TEXT(A10, "mmm") -> Jan | F10: =YEAR(Table7[[#This Row],[date]]) -> 2023
A11: 2023-01-04 | B11: Inventory | C11: Purchase of Chargers | D11: 49594 | E11: =TEXT(A11, "mmm") -> Jan | F11: =YEAR(Table7[[#This Row],[date]]) -> 2023
A12: 2023-01-04 | B12: Transportation | C12: Fuel Purchase | D12: 13501 | E12: =TEXT(A12, "mmm") -> Jan | F12: =YEAR(Table7[[#This Row],[date]]) -> 2023
A13: 2023-01-07 | B13: Transportation | C13: Fuel Purchase | D13: 9806 | E13: =TEXT(A13, "mmm") -> Jan | F13: =YEAR(Table7[[#This Row],[date]]) -> 2023
... A3001: 2025-12-31 | B3001: Rent | C3001: Office Rent | D3001: 105895 | E3001: =TEXT(A3001, "mmm") -> Dec | F3001: =YEAR(Table7[[#This Row],[date]]) -> 2025

Sheet PIVOT TABLE
A1: SALES BY MONTH | D1: EXPENSES BY MONTH | G1: SALES BY CATEGORY | J1: TOP 5 PRODUCTS | M1: EXPENSES BY CATEGORY
A2: Row Labels | B2: Sum of total_amount | D2: Row Labels | E2: Sum of amount | G2: Row Labels | H2: Sum of total_amount | J2: Row Labels | K2: Sum of total_amount | M2: Row Labels | N2: Sum of amount
A3: Jan | B3: 49014900 | D3: Jan | E3: 7559186 | G3: BATTERIES & POWER BANKS | H3: 82760500 | J3: TECNO T101 | K3: 24534000 | M3: Inventory | N3: 13720171
A4: Feb | B4: 50220600 | D4: Feb | E4: 8466359 | G4: CAR MP | H4: 10649000 | J4: HEADSET CK-129 | K4: 32934000 | M4: Maintenance | N4: 4967518
A5: Mar | B5: 64690200 | D5: Mar | E5: 7225226 | G5: CHARGERS | H5: 28930000 | J5: ORAIMO 30000mAh | K5: 40376000 | M5: Marketing | N5: 6486172
A6: Apr | B6: 48990500 | D6: Apr | E6: 6995803 | G6: CORDS | H6: 10523500 | J6: INFINIX SMART10 | K6: 152835000 | M6: Miscellaneous | N6: 2184264
A7: May | B7: 60366400 | D7: May | E7: 7157525 | G7: EAR PHONES | H7: 65274500 | J7: TECNO SPARK 40 | K7: 200100000 | M7: Rent | N7: 37636440
A8: Jun | B8: 47598000 | D8: Jun | E8: 7153645 | G8: MOUSE | H8: 23510000 | J8: Grand Total | K8: 450779000 | M8: Salaries | N8: 15129361
A9: Jul | B9: 44968700 | D9: Jul | E9: 6987630 | G9: PHONES | H9: 395585000 | M9: Transportation | N9: 2954058
A10: Aug | B10: 52659400 | D10: Aug | E10: 7063684 | G10: PHONES PATCH | H10: 15501500 | M10: Utilities | N10: 4381478
A11: Sept | B11: 56078000 | D11: Sept | E11: 7363269 | G11: SCREEN GUARD | H11: 10183500 | M11: Grand Total | N11: 87459462
A12: Oct | B12: 44469700 | D12: Oct | E12: 7425541 | G12: Grand Total | H12: 642917500
A13: Nov | B13: 69037000 | D13: Nov | E13: 7393474
A14: Dec | B14: 54824100 | D14: Dec | E14: 6668120
A15: Grand Total | B15: 642917500 | D15: Grand Total | E15: 87459462
G16: SUM OF EXPENSES | I16: SUM OF SALES | K16: TOTAL PROFIT | M16: TOTAL TRANSACTION | O16: PROFIT MARGIN
G17: Sum of amount | I17: Sum of total_amount | K17: =GETPIVOTDATA("total_amount",$I$17)-GETPIVOTDATA("amount",$G$17) -> 555458038 | M17: =COUNTA(Table1[sales_id]) -> 6000 | O17: =K17/GETPIVOTDATA("total_amount",$I$17) -> 0.86396472
G18: 87459462 | I18: 642917500
I23: expenses | J23: amount
I24: Inventory | J24: =GETPIVOTDATA("amount",$M$2,"expenses_category",M3) -> 13720171
I25: Maintenance | J25: =GETPIVOTDATA("amount",$M$2,"expenses_category",M4) -> 4967518
I26: Marketing | J26: =GETPIVOTDATA("amount",$M$2,"expenses_category",M5) -> 6486172
I27: Miscellaneous | J27: =GETPIVOTDATA("amount",$M$2,"expenses_category",M6) -> 2184264
I28: Rent | J28: =GETPIVOTDATA("amount",$M$2,"expenses_category",M7) -> 37636440
I29: Salaries | J29: =GETPIVOTDATA("amount",$M$2,"expenses_category",M8) -> 15129361
I30: Transportation | J30: =GETPIVOTDATA("amount",$M$2,"expenses_category",M9) -> 2954058
I31: Utilities | J31: =GETPIVOTDATA("amount",$M$2,"expenses_category",M10) -> 4381478

Sheet PROFIT ANALYSIS
A1: Month | B1: Total Sales | C1: Total Expenses | D1: Profit
A2: {=_xlfn.UNIQUE(Table1[[#This Row],[months]])} -> Jan | B2: =SUMIFS(Table1[total_amount],Table1[months], A2) -> 49014900 | C2: =SUMIFS(Table7[amount],Table7[month], A2) -> 7559186 | D2: =B2-C2 -> 41455714
A3: {=_xlfn.UNIQUE(SALES!H5)} -> Feb | B3: =SUMIFS(Table1[total_amount],Table1[months], A3) -> 50220600 | C3: =SUMIFS(Table7[amount],Table7[month], A3) -> 8466359 | D3: =B3-C3 -> 41754241
A4: {=_xlfn.UNIQUE(SALES!H6)} -> Mar | B4: =SUMIFS(Table1[total_amount],Table1[months], A4) -> 64690200 | C4: =SUMIFS(Table7[amount],Table7[month], A4) -> 7225226 | D4: =B4-C4 -> 57464974
A5: {=_xlfn.UNIQUE(SALES!H9)} -> Apr | B5: =SUMIFS(Table1[total_amount],Table1[months], A5) -> 48990500 | C5: =SUMIFS(Table7[amount],Table7[month], A5) -> 6995803 | D5: =B5-C5 -> 41994697
A6: {=_xlfn.UNIQUE(SALES!H12)} -> May | B6: =SUMIFS(Table1[total_amount],Table1[months], A6) -> 60366400 | C6: =SUMIFS(Table7[amount],Table7[month], A6) -> 7157525 | D6: =B6-C6 -> 53208875
A7: {=_xlfn.UNIQUE(SALES!H15)} -> Jun | B7: =SUMIFS(Table1[total_amount],Table1[months], A7) -> 47598000 | C7: =SUMIFS(Table7[amount],Table7[month], A7) -> 7153645 | D7: =B7-C7 -> 40444355
A8: {=_xlfn.UNIQUE(SALES!H17)} -> Jul | B8: =SUMIFS(Table1[total_amount],Table1[months], A8) -> 44968700 | C8: =SUMIFS(Table7[amount],Table7[month], A8) -> 6987630 | D8: =B8-C8 -> 37981070
A9: {=_xlfn.UNIQUE(SALES!H18)} -> Aug | B9: =SUMIFS(Table1[total_amount],Table1[months], A9) -> 52659400 | C9: =SUMIFS(Table7[amount],Table7[month], A9) -> 7063684 | D9: =B9-C9 -> 45595716
A10: {=_xlfn.UNIQUE(SALES!H20)} -> Sept | B10: =SUMIFS(Table1[total_amount],Table1[months], A10) -> 56078000 | C10: =SUMIFS(Table7[amount],Table7[month], A10) -> 7363269 | D10: =B10-C10 -> 48714731
A11: {=_xlfn.UNIQUE(SALES!H21)} -> Oct | B11: =SUMIFS(Table1[total_amount],Table1[months], A11) -> 44469700 | C11: =SUMIFS(Table7[amount],Table7[month], A11) -> 7425541 | D11: =B11-C11 -> 37044159
A12: {=_xlfn.UNIQUE(SALES!H22)} -> Nov | B12: =SUMIFS(Table1[total_amount],Table1[months], A12) -> 69037000 | C12: =SUMIFS(Table7[amount],Table7[month], A12) -> 7393474 | D12: =B12-C12 -> 61643526
A13: {=_xlfn.UNIQUE(SALES!H24)} -> Dec | B13: =SUMIFS(Table1[total_amount],Table1[months], A13) -> 54824100 | C13: =SUMIFS(Table7[amount],Table7[month], A13) -> 6668120 | D13: =B13-C13 -> 48155980

Sheet DASHBOARD
